{
	"pages": [ 
		{
			"path": "pages/index/index",
			"style": {
				"navigationBarTitleText": "我的词库",
				"navigationBarTextStyle": "black",
				"navigationBarBackgroundColor": "#FFFFFF"
			}
		},
		{
			"path": "pages/wordList/wordList",
			"style": {
				"navigationBarTitleText": "不规则动词",
				"navigationBarTextStyle": "black",
				"navigationBarBackgroundColor": "#FFFFFF"
			}
		},
		{
			"path": "pages/highWord/highWord",
			"style": {
				"navigationBarTitleText": "牛津高中英语",
				"navigationBarTextStyle": "black",
				"navigationBarBackgroundColor": "#FFFFFF"
			}
		}
	],
	"globalStyle": {
		"navigationBarTextStyle": "black",
		"navigationBarBackgroundColor": "#F8F8F8",
		"backgroundColor": "#F8F8F8"
	},
	"uniIdRouter": {},
	"easycom": {
		"autoscan": true,
		"custom": {
			"^uni-(.*)": "@dcloudio/uni-ui/lib/uni-$1/uni-$1.vue"
		}
	}
}
